robot_math/ROBOT_MATH.py
robot_math/__init__.py
robot_math/tests/RF_MATH_SEJFTEST.robot
robot_math/tests/__init__.py
robot_math/tests/log.html
robot_math/tests/report.html
robot_math/tests/unittests/__init__.py
robot_math/tests/unittests/test_data_packet.py
robot_math/tests/unittests/test_packet_size.py
robot_math/tests/unittests/test_percent.py
robot_math/tests/unittests/test_robot_time.py
robot_math/types/__init__.py
robot_math/types/data_packet_type.py
robot_math/types/percent_type.py
robot_math/types/time_interval_type.py
robot_math/types/abstracts/__init__.py
robot_math/types/abstracts/operators.py
robot_math/types/abstracts/special_type_abs.py
robot_math/types/cross_type_operators/__init__.py
robotframework_calculator-2.2.dist-info/LICENSE
robotframework_calculator-2.2.dist-info/METADATA
robotframework_calculator-2.2.dist-info/WHEEL
robotframework_calculator-2.2.dist-info/top_level.txt
robotframework_calculator-2.2.dist-info/RECORD
