Metadata-Version: 2.1
Name: robotframework-calculator
Version: 2.2
Summary: Extension for Robotframework converting data packet, time str and percent into numeric objects
Home-page: https://github.com/doguz2509/robotframework-calculator
Author: Dmitry Oguz
Author-email: doguz2509@gmail.com
License: MIT
Platform: UNKNOWN
Classifier: License :: OSI Approved :: MIT License
Classifier: Operating System :: OS Independent
Classifier: Programming Language :: Python :: 2.7
Classifier: Programming Language :: Python :: 3
Classifier: Programming Language :: Python :: 3.5
Classifier: Programming Language :: Python :: 3.6
Classifier: Programming Language :: Python :: 3.7
Classifier: Programming Language :: Python :: 3.8
Requires-Dist: robotframework (>3)
